fastresta/__init__.py
fastresta/flask_app.py
fastresta/flask_boot.py
fastresta/provider.py
fastresta/annotations/__init__.py
fastresta/annotations/component.py
fastresta/annotations/inject.py
fastresta/annotations/service.py
fastresta/dependency_container/__init__.py
fastresta/dependency_container/component_registry.py
fastresta/dependency_container/container.py
fastresta/dependency_container/controller_registry.py
fastresta/dependency_container/dependency_registry.py
fastresta/dependency_container/registry.py
fastresta/utils/__init__.py
fastresta/utils/sort.py
fastresta/web/__init__.py
fastresta/web/delete.py
fastresta/web/get.py
fastresta/web/post.py
fastresta/web/put.py
fastresta/web/rest_controller.py
fastresta-0.0.1.dist-info/LICENSE.txt
fastresta-0.0.1.dist-info/METADATA
fastresta-0.0.1.dist-info/WHEEL
fastresta-0.0.1.dist-info/top_level.txt
fastresta-0.0.1.dist-info/RECORD
